flask_maoko.py
Flask_Maoko-0.1.1.dist-info/DESCRIPTION.rst
Flask_Maoko-0.1.1.dist-info/METADATA
Flask_Maoko-0.1.1.dist-info/metadata.json
Flask_Maoko-0.1.1.dist-info/RECORD
Flask_Maoko-0.1.1.dist-info/top_level.txt
Flask_Maoko-0.1.1.dist-info/WHEEL
flaskext/__init__.py
