Metadata-Version: 2.0
Name: Flask-Maoko
Version: 0.1.1
Summary: Mako templating support for Flask applications.
Home-page: https://github.com/GuoJing/flask-maoko
Author: Beranger Enselme, Frank Murphy, GuoJing
Author-email: soundbbg@gmail.com
License: BSD
Platform: any
Classifier: Development Status :: 3 - Alpha
Classifier: Environment :: Web Environment
Classifier: Intended Audience :: Developers
Classifier: License :: OSI Approved :: BSD License
Classifier: Operating System :: OS Independent
Classifier: Programming Language :: Python
Classifier: Programming Language :: Python :: 3
Classifier: Topic :: Internet :: WWW/HTTP :: Dynamic Content
Classifier: Topic :: Software Development :: Libraries :: Python Modules
Requires-Dist: Flask
Requires-Dist: Mako
